gen_func/__init__.py
gen_func/gpt_actions.py
gen_func/main.py
gen_func/meta_parsing.py
gen_func/prompts.py
gen_func/validation.py
gen_func-1.0.1.dist-info/METADATA
gen_func-1.0.1.dist-info/WHEEL
gen_func-1.0.1.dist-info/top_level.txt
gen_func-1.0.1.dist-info/RECORD
